actuarialmath/__init__.py
actuarialmath/actuarial.py
actuarialmath/annuity.py
actuarialmath/constantforce.py
actuarialmath/extrarisk.py
actuarialmath/fractional.py
actuarialmath/insurance.py
actuarialmath/interest.py
actuarialmath/life.py
actuarialmath/lifetable.py
actuarialmath/lifetime.py
actuarialmath/mortalitylaws.py
actuarialmath/mthly.py
actuarialmath/policyvalues.py
actuarialmath/premiums.py
actuarialmath/recursion.py
actuarialmath/reserves.py
actuarialmath/selectlife.py
actuarialmath/sult.py
actuarialmath/survival.py
actuarialmath/udd.py
actuarialmath/woolhouse.py
actuarialmath-1.0.1.dist-info/LICENSE
actuarialmath-1.0.1.dist-info/METADATA
actuarialmath-1.0.1.dist-info/WHEEL
actuarialmath-1.0.1.dist-info/top_level.txt
actuarialmath-1.0.1.dist-info/RECORD
