Metadata-Version: 2.1
Name: actuarialmath
Version: 1.0.1
Summary: A package for solving actuarial math and life contingent risks
Author: Terence Lim
Project-URL: Homepage, https://github.com/terence-lim/actuarialmath
Project-URL: Bug Tracker, https://github.com/terence-lim/actuarialmath/issues
Classifier: Programming Language :: Python :: 3
Classifier: License :: OSI Approved :: MIT License
Classifier: Operating System :: OS Independent
Requires-Python: >=3.10
License-File: LICENSE
Requires-Dist: matplotlib >=3.7.1
Requires-Dist: numpy >=1.22.4
Requires-Dist: pandas >=1.5.3
Requires-Dist: scipy >=1.10.1
